pubgator/__init__.py
pubgator/client.py
pubgator/models.py
pubgator/requests/entity.py
pubgator/requests/export.py
pubgator/requests/relations.py
pubgator/requests/search.py
pubgator-0.3.0.dist-info/METADATA
pubgator-0.3.0.dist-info/WHEEL
pubgator-0.3.0.dist-info/licenses/LICENSE
pubgator-0.3.0.dist-info/RECORD
