Metadata-Version: 2.4
Name: pubgator
Version: 0.3.0
Author-email: Felix Wiegand <felix.wiegand@tu-dortmund.de>
License-File: LICENSE
Requires-Python: >=3.11
Requires-Dist: bioc<3,>=2.1
Requires-Dist: httpx<0.29,>=0.28.1
